[{"country-id":"AF","slug":"afghanistan","latitude":33,"longitude":65,"name":"Afghanistan","tree-cover-loss":244,"tree-cover-loss-percent-per-year":0.0002,"redd-plus-finance":0,"development-finance":0,"results-based-finance-commitments":0},{"country-id":"AL","slug":"albania","latitude":41,"longitude":20,"name":"Albania","tree-cover-loss":11145,"tree-cover-loss-percent-per-year":0.0029,"redd-plus-finance":0,"development-finance":6,"results-based-finance-commitments":0},{"country-id":"DZ","slug":"algeria","latitude":28,"longitude":3,"name":"Algeria","tree-cover-loss":44019,"tree-cover-loss-percent-per-year":0.006,"redd-plus-finance":0,"development-finance":0,"results-based-finance-commitments":0},{"country-id":"AD","slug":"andorra","latitude":42.5,"longitude":1.5,"name":"Andorra","tree-cover-loss":17,"tree-cover-loss-percent-per-year":0.0001,"redd-plus-finance":0,"development-finance":null,"results-based-finance-commitments":0},{"country-id":"AO","slug":"angola","latitude":-12.5,"longitude":18.5,"name":"Angola","tree-cover-loss":1067688,"tree-cover-loss-percent-per-year":0.0032,"redd-plus-finance":0,"development-finance":5,"results-based-finance-commitments":0},{"country-id":"AG","slug":"antigua-and-barbuda","latitude":17,"longitude":-61.5,"name":"Antigua and Barbuda","tree-cover-loss":133,"tree-cover-loss-percent-per-year":0.0012,"redd-plus-finance":0,"development-finance":null,"results-based-finance-commitments":0},{"country-id":"AR","slug":"argentina","latitude":-34,"longitude":-64,"name":"Argentina","tree-cover-loss":2188708,"tree-cover-loss-percent-per-year":0.0093,"redd-plus-finance":8,"development-finance":89,"results-based-finance-commitments":0},{"country-id":"AM","slug":"armenia","latitude":40,"longitude":45,"name":"Armenia","tree-cover-loss":616,"tree-cover-loss-percent-per-year":0.0003,"redd-plus-finance":0,"development-finance":4,"results-based-finance-commitments":0},{"country-id":"AZ","slug":"azerbaijan","latitude":40.5,"longitude":47.5,"name":"Azerbaijan","tree-cover-loss":1799,"tree-cover-loss-percent-per-year":0.0002,"redd-plus-finance":0,"development-finance":null,"results-based-finance-commitments":0},{"country-id":"BS","slug":"bahamas","latitude":25,"longitude":-77.3,"name":"Bahamas","tree-cover-loss":4960,"tree-cover-loss-percent-per-year":0.0027,"redd-plus-finance":0,"development-finance":null,"results-based-finance-commitments":0},{"country-id":"BD","slug":"bangladesh","latitude":24,"longitude":90,"name":"Bangladesh","tree-cover-loss":45689,"tree-cover-loss-percent-per-year":0.0039,"redd-plus-finance":2,"development-finance":4,"results-based-finance-commitments":0},{"country-id":"BB","slug":"barbados","latitude":13,"longitude":-59.5,"name":"Barbados","tree-cover-loss":162,"tree-cover-loss-percent-per-year":0.0051,"redd-plus-finance":0,"development-finance":null,"results-based-finance-commitments":0},{"country-id":"BZ","slug":"belize","latitude":17.25,"longitude":-88.77,"name":"Belize","tree-cover-loss":92788,"tree-cover-loss-percent-per-year":0.0088,"redd-plus-finance":4,"development-finance":null,"results-based-finance-commitments":0},{"country-id":"BJ","slug":"benin","latitude":9.5,"longitude":2.25,"name":"Benin","tree-cover-loss":7319,"tree-cover-loss-percent-per-year":0.0072,"redd-plus-finance":0,"development-finance":0,"results-based-finance-commitments":0},{"country-id":"BT","slug":"bhutan","latitude":27.5,"longitude":90.5,"name":"Bhutan","tree-cover-loss":8672,"tree-cover-loss-percent-per-year":0.0006,"redd-plus-finance":4.570465,"development-finance":3,"results-based-finance-commitments":0},{"country-id":"BO","slug":"bolivia","latitude":-17,"longitude":-65,"name":"Bolivia","tree-cover-loss":1658542,"tree-cover-loss-percent-per-year":0.0043,"redd-plus-finance":1,"development-finance":22,"results-based-finance-commitments":0},{"country-id":"BA","slug":"bosnia-and-herzegovina","latitude":44,"longitude":18,"name":"Bosnia and Herzegovina","tree-cover-loss":9259,"tree-cover-loss-percent-per-year":0.0006,"redd-plus-finance":0,"development-finance":null,"results-based-finance-commitments":0},{"country-id":"BW","slug":"botswana","latitude":-22,"longitude":24,"name":"Botswana","tree-cover-loss":97,"tree-cover-loss-percent-per-year":0.0008,"redd-plus-finance":0,"development-finance":3,"results-based-finance-commitments":0},{"country-id":"BR","slug":"brazil","latitude":-10,"longitude":-55,"name":"Brazil","tree-cover-loss":14392306,"tree-cover-loss-percent-per-year":0.0046,"redd-plus-finance":93,"development-finance":247,"results-based-finance-commitments":1167},{"country-id":"BN","slug":"brunei","latitude":4.5,"longitude":114.6667,"name":"Brunei","tree-cover-loss":10298,"tree-cover-loss-percent-per-year":0.0032,"redd-plus-finance":0,"development-finance":null,"results-based-finance-commitments":0},{"country-id":"BF","slug":"burkina-faso","latitude":13,"longitude":-2,"name":"Burkina Faso","tree-cover-loss":23,"tree-cover-loss-percent-per-year":0.0289,"redd-plus-finance":42,"development-finance":18,"results-based-finance-commitments":0},{"country-id":"BI","slug":"burundi","latitude":-3.5,"longitude":30,"name":"Burundi","tree-cover-loss":8648,"tree-cover-loss-percent-per-year":0.0027,"redd-plus-finance":0,"development-finance":0,"results-based-finance-commitments":0},{"country-id":"KH","slug":"cambodia","latitude":13,"longitude":105,"name":"Cambodia","tree-cover-loss":1110207,"tree-cover-loss-percent-per-year":0.021,"redd-plus-finance":12.86316,"development-finance":8,"results-based-finance-commitments":0},{"country-id":"CM","slug":"cameroon","latitude":6,"longitude":12,"name":"Cameroon","tree-cover-loss":482345,"tree-cover-loss-percent-per-year":0.0026,"redd-plus-finance":6.8,"development-finance":89,"results-based-finance-commitments":57.5},{"country-id":"CV","slug":"cape-verde","latitude":16,"longitude":-24,"name":"Cape Verde","tree-cover-loss":40,"tree-cover-loss-percent-per-year":0.0009,"redd-plus-finance":0,"development-finance":null,"results-based-finance-commitments":0},{"country-id":"CF","slug":"central-african-republic","latitude":7,"longitude":21,"name":"Central African Republic","tree-cover-loss":284501,"tree-cover-loss-percent-per-year":0.001,"redd-plus-finance":4,"development-finance":1,"results-based-finance-commitments":0},{"country-id":"TD","slug":"chad","latitude":15,"longitude":19,"name":"Chad","tree-cover-loss":12153,"tree-cover-loss-percent-per-year":0.0049,"redd-plus-finance":0,"development-finance":12,"results-based-finance-commitments":0},{"country-id":"CL","slug":"chile","latitude":-30,"longitude":-71,"name":"Chile","tree-cover-loss":693339,"tree-cover-loss-percent-per-year":0.006,"redd-plus-finance":10.9047,"development-finance":1,"results-based-finance-commitments":26},{"country-id":"CN","slug":"china","latitude":35,"longitude":105,"name":"China","tree-cover-loss":3294610,"tree-cover-loss-percent-per-year":0.0034,"redd-plus-finance":0,"development-finance":290,"results-based-finance-commitments":0},{"country-id":"CO","slug":"colombia","latitude":4,"longitude":-72,"name":"Colombia","tree-cover-loss":1095381,"tree-cover-loss-percent-per-year":0.0022,"redd-plus-finance":31.721,"development-finance":66,"results-based-finance-commitments":308.1784},{"country-id":"KM","slug":"comoros","latitude":-12.1667,"longitude":44.25,"name":"Comoros","tree-cover-loss":3975,"tree-cover-loss-percent-per-year":0.0049,"redd-plus-finance":0,"development-finance":null,"results-based-finance-commitments":0},{"country-id":"CR","slug":"costa-rica","latitude":10,"longitude":-84,"name":"Costa Rica","tree-cover-loss":56028,"tree-cover-loss-percent-per-year":0.0024,"redd-plus-finance":11.214,"development-finance":1,"results-based-finance-commitments":60},{"country-id":"CI","slug":"cote-d-ivoire","latitude":8,"longitude":-5,"name":"Côte d'Ivoire","tree-cover-loss":988288,"tree-cover-loss-percent-per-year":0.0111,"redd-plus-finance":18.431,"development-finance":17,"results-based-finance-commitments":82.5},{"country-id":"CU","slug":"cuba","latitude":21.5,"longitude":-80,"name":"Cuba","tree-cover-loss":53925,"tree-cover-loss-percent-per-year":0.0022,"redd-plus-finance":0,"development-finance":0,"results-based-finance-commitments":0},{"country-id":"CD","slug":"democratic-republic-of-congo","latitude":0,"longitude":25,"name":"Democratic Republic of Congo","tree-cover-loss":5056326,"tree-cover-loss-percent-per-year":0.0042,"redd-plus-finance":104.788,"development-finance":75,"results-based-finance-commitments":50},{"country-id":"DM","slug":"dominica","latitude":15.3,"longitude":-61.4,"name":"Dominica","tree-cover-loss":318,"tree-cover-loss-percent-per-year":0.0007,"redd-plus-finance":0,"development-finance":null,"results-based-finance-commitments":0},{"country-id":"DO","slug":"dominican-republic","latitude":19,"longitude":-70.6667,"name":"Dominican Republic","tree-cover-loss":86440,"tree-cover-loss-percent-per-year":0.0056,"redd-plus-finance":4.89316,"development-finance":1,"results-based-finance-commitments":37.5},{"country-id":"EC","slug":"ecuador","latitude":-2,"longitude":-77.5,"name":"Ecuador","tree-cover-loss":261847,"tree-cover-loss-percent-per-year":0.0023,"redd-plus-finance":45,"development-finance":14,"results-based-finance-commitments":90},{"country-id":"EG","slug":"egypt","latitude":27,"longitude":30,"name":"Egypt","tree-cover-loss":883,"tree-cover-loss-percent-per-year":0.001,"redd-plus-finance":0,"development-finance":null,"results-based-finance-commitments":0},{"country-id":"SV","slug":"el-salvador","latitude":13.8333,"longitude":-88.9167,"name":"El Salvador","tree-cover-loss":15413,"tree-cover-loss-percent-per-year":0.0026,"redd-plus-finance":4,"development-finance":1,"results-based-finance-commitments":0},{"country-id":"GQ","slug":"equatorial-guinea","latitude":2,"longitude":10,"name":"Equatorial Guinea","tree-cover-loss":53221,"tree-cover-loss-percent-per-year":0.0033,"redd-plus-finance":0,"development-finance":1,"results-based-finance-commitments":0},{"country-id":"ET","slug":"ethiopia","latitude":8,"longitude":38,"name":"Ethiopia","tree-cover-loss":151132,"tree-cover-loss-percent-per-year":0.0021,"redd-plus-finance":105,"development-finance":39,"results-based-finance-commitments":50},{"country-id":"FJ","slug":"fiji","latitude":-18,"longitude":175,"name":"Fiji","tree-cover-loss":12346,"tree-cover-loss-percent-per-year":0.0013,"redd-plus-finance":4.013572,"development-finance":1,"results-based-finance-commitments":18},{"country-id":"GA","slug":"gabon","latitude":-1,"longitude":11.75,"name":"Gabon","tree-cover-loss":164985,"tree-cover-loss-percent-per-year":0.0011,"redd-plus-finance":0,"development-finance":12,"results-based-finance-commitments":0},{"country-id":"GM","slug":"gambia","latitude":13.4667,"longitude":-16.5667,"name":"Gambia","tree-cover-loss":135,"tree-cover-loss-percent-per-year":0.0049,"redd-plus-finance":0,"development-finance":null,"results-based-finance-commitments":0},{"country-id":"GE","slug":"georgia","latitude":42,"longitude":43.5,"name":"Georgia","tree-cover-loss":2240,"tree-cover-loss-percent-per-year":0.0001,"redd-plus-finance":0,"development-finance":8,"results-based-finance-commitments":0},{"country-id":"GH","slug":"ghana","latitude":8,"longitude":-2,"name":"Ghana","tree-cover-loss":351302,"tree-cover-loss-percent-per-year":0.0084,"redd-plus-finance":83.755525,"development-finance":24,"results-based-finance-commitments":92.5},{"country-id":"GD","slug":"grenada","latitude":12,"longitude":-61.75,"name":"Grenada","tree-cover-loss":355,"tree-cover-loss-percent-per-year":0.0021,"redd-plus-finance":0,"development-finance":null,"results-based-finance-commitments":0},{"country-id":"GT","slug":"guatemala","latitude":15.5,"longitude":-90.25,"name":"Guatemala","tree-cover-loss":355427,"tree-cover-loss-percent-per-year":0.0077,"redd-plus-finance":9.591544,"development-finance":3,"results-based-finance-commitments":52.5},{"country-id":"GN","slug":"guinea","latitude":11,"longitude":-10,"name":"Guinea","tree-cover-loss":508889,"tree-cover-loss-percent-per-year":0.0104,"redd-plus-finance":0,"development-finance":null,"results-based-finance-commitments":0},{"country-id":"GW","slug":"guinea-bissau","latitude":12,"longitude":-15,"name":"Guinea-Bissau","tree-cover-loss":58920,"tree-cover-loss-percent-per-year":0.0092,"redd-plus-finance":0,"development-finance":0,"results-based-finance-commitments":0},{"country-id":"GY","slug":"guyana","latitude":5,"longitude":-59,"name":"Guyana","tree-cover-loss":63929,"tree-cover-loss-percent-per-year":0.0006,"redd-plus-finance":73.73769,"development-finance":1,"results-based-finance-commitments":200},{"country-id":"HT","slug":"haiti","latitude":19,"longitude":-72.4167,"name":"Haiti","tree-cover-loss":19049,"tree-cover-loss-percent-per-year":0.0037,"redd-plus-finance":0,"development-finance":3,"results-based-finance-commitments":0},{"country-id":"HN","slug":"honduras","latitude":15,"longitude":-86.5,"name":"Honduras","tree-cover-loss":282318,"tree-cover-loss-percent-per-year":0.0061,"redd-plus-finance":7,"development-finance":31,"results-based-finance-commitments":0},{"country-id":"IN","slug":"india","latitude":20,"longitude":77,"name":"India","tree-cover-loss":570462,"tree-cover-loss-percent-per-year":0.0024,"redd-plus-finance":0,"development-finance":372,"results-based-finance-commitments":0},{"country-id":"ID","slug":"indonesia","latitude":-5,"longitude":120,"name":"Indonesia","tree-cover-loss":9872937,"tree-cover-loss-percent-per-year":0.0102,"redd-plus-finance":245.719,"development-finance":181,"results-based-finance-commitments":972},{"country-id":"IR","slug":"iran","latitude":32,"longitude":53,"name":"Iran","tree-cover-loss":992,"tree-cover-loss-percent-per-year":0.0001,"redd-plus-finance":0,"development-finance":6,"results-based-finance-commitments":0},{"country-id":"IQ","slug":"iraq","latitude":33,"longitude":44,"name":"Iraq","tree-cover-loss":30,"tree-cover-loss-percent-per-year":0.0003,"redd-plus-finance":0,"development-finance":null,"results-based-finance-commitments":0},{"country-id":"IL","slug":"israel","latitude":31.5,"longitude":34.75,"name":"Israel","tree-cover-loss":1423,"tree-cover-loss-percent-per-year":0.008,"redd-plus-finance":0,"development-finance":null,"results-based-finance-commitments":0},{"country-id":"JM","slug":"jamaica","latitude":18.25,"longitude":-77.5,"name":"Jamaica","tree-cover-loss":14423,"tree-cover-loss-percent-per-year":0.0031,"redd-plus-finance":0,"development-finance":null,"results-based-finance-commitments":0},{"country-id":"JO","slug":"jordan","latitude":31,"longitude":36,"name":"Jordan","tree-cover-loss":1,"tree-cover-loss-percent-per-year":0.0001,"redd-plus-finance":0,"development-finance":null,"results-based-finance-commitments":0},{"country-id":"KZ","slug":"kazakhstan","latitude":48,"longitude":68,"name":"Kazakhstan","tree-cover-loss":15343,"tree-cover-loss-percent-per-year":0.0006,"redd-plus-finance":0,"development-finance":null,"results-based-finance-commitments":0},{"country-id":"KE","slug":"kenya","latitude":1,"longitude":38,"name":"Kenya","tree-cover-loss":102428,"tree-cover-loss-percent-per-year":0.0051,"redd-plus-finance":4,"development-finance":18,"results-based-finance-commitments":0},{"country-id":"KG","slug":"kyrgyzstan","latitude":41,"longitude":75,"name":"Kyrgyzstan","tree-cover-loss":498,"tree-cover-loss-percent-per-year":0.0001,"redd-plus-finance":0,"development-finance":4,"results-based-finance-commitments":0},{"country-id":"LA","slug":"laos","latitude":18,"longitude":105,"name":"Laos","tree-cover-loss":1179888,"tree-cover-loss-percent-per-year":0.0103,"redd-plus-finance":81.0077,"development-finance":73,"results-based-finance-commitments":42},{"country-id":"LB","slug":"lebanon","latitude":33.8333,"longitude":35.8333,"name":"Lebanon","tree-cover-loss":918,"tree-cover-loss-percent-per-year":0.0023,"redd-plus-finance":0,"development-finance":2,"results-based-finance-commitments":0},{"country-id":"LS","slug":"lesotho","latitude":-29.5,"longitude":28.5,"name":"Lesotho","tree-cover-loss":31,"tree-cover-loss-percent-per-year":0.0009,"redd-plus-finance":0,"development-finance":0,"results-based-finance-commitments":0},{"country-id":"LR","slug":"liberia","latitude":6.5,"longitude":-9.5,"name":"Liberia","tree-cover-loss":632510,"tree-cover-loss-percent-per-year":0.0112,"redd-plus-finance":9,"development-finance":21,"results-based-finance-commitments":62},{"country-id":"LY","slug":"libya","latitude":25,"longitude":17,"name":"Libya","tree-cover-loss":110,"tree-cover-loss-percent-per-year":0.0027,"redd-plus-finance":0,"development-finance":null,"results-based-finance-commitments":0},{"country-id":"MK","slug":"macedonia","latitude":42,"longitude":21.4,"name":"Macedonia","tree-cover-loss":11067,"tree-cover-loss-percent-per-year":0.0024,"redd-plus-finance":0,"development-finance":3,"results-based-finance-commitments":0},{"country-id":"MG","slug":"madagascar","latitude":-20,"longitude":47,"name":"Madagascar","tree-cover-loss":1415832,"tree-cover-loss-percent-per-year":0.0138,"redd-plus-finance":9.312,"development-finance":3,"results-based-finance-commitments":82},{"country-id":"MW","slug":"malawi","latitude":-13.5,"longitude":34,"name":"Malawi","tree-cover-loss":64306,"tree-cover-loss-percent-per-year":0.007,"redd-plus-finance":0,"development-finance":32,"results-based-finance-commitments":0},{"country-id":"MY","slug":"malaysia","latitude":2.5,"longitude":112.5,"name":"Malaysia","tree-cover-loss":2953610,"tree-cover-loss-percent-per-year":0.0167,"redd-plus-finance":0,"development-finance":6,"results-based-finance-commitments":0},{"country-id":"MV","slug":"maldives","latitude":4.15,"longitude":73.5,"name":"Maldives","tree-cover-loss":23,"tree-cover-loss-percent-per-year":0.0007,"redd-plus-finance":0,"development-finance":null,"results-based-finance-commitments":0},{"country-id":"ML","slug":"mali","latitude":17,"longitude":-4,"name":"Mali","tree-cover-loss":1183,"tree-cover-loss-percent-per-year":0.0079,"redd-plus-finance":0,"development-finance":18,"results-based-finance-commitments":0},{"country-id":"MU","slug":"mauritius","latitude":-20.2833,"longitude":57.55,"name":"Mauritius","tree-cover-loss":1414,"tree-cover-loss-percent-per-year":0.0033,"redd-plus-finance":0,"development-finance":null,"results-based-finance-commitments":0},{"country-id":"MX","slug":"mexico","latitude":23,"longitude":-102,"name":"Mexico","tree-cover-loss":1115702,"tree-cover-loss-percent-per-year":0.0035,"redd-plus-finance":97.774,"development-finance":11,"results-based-finance-commitments":73.5},{"country-id":"FM","slug":"micronesia","latitude":6.9,"longitude":158.3,"name":"Micronesia","tree-cover-loss":77,"tree-cover-loss-percent-per-year":0.0021,"redd-plus-finance":0,"development-finance":null,"results-based-finance-commitments":0},{"country-id":"MD","slug":"moldova","latitude":47,"longitude":29,"name":"Moldova","tree-cover-loss":3161,"tree-cover-loss-percent-per-year":0.0015,"redd-plus-finance":0,"development-finance":null,"results-based-finance-commitments":0},{"country-id":"MN","slug":"mongolia","latitude":46,"longitude":105,"name":"Mongolia","tree-cover-loss":55252,"tree-cover-loss-percent-per-year":0.0023,"redd-plus-finance":4,"development-finance":12,"results-based-finance-commitments":0},{"country-id":"ME","slug":"montenegro","latitude":42.5,"longitude":19.4,"name":"Montenegro","tree-cover-loss":5984,"tree-cover-loss-percent-per-year":0.0016,"redd-plus-finance":0,"development-finance":2,"results-based-finance-commitments":0},{"country-id":"MA","slug":"morocco","latitude":32,"longitude":-5,"name":"Morocco","tree-cover-loss":9541,"tree-cover-loss-percent-per-year":0.0025,"redd-plus-finance":0,"development-finance":48,"results-based-finance-commitments":0},{"country-id":"MZ","slug":"mozambique","latitude":-18.25,"longitude":35,"name":"Mozambique","tree-cover-loss":1029277,"tree-cover-loss-percent-per-year":0.0059,"redd-plus-finance":9,"development-finance":67,"results-based-finance-commitments":43.5},{"country-id":"MM","slug":"myanmar","latitude":22,"longitude":98,"name":"Myanmar","tree-cover-loss":1403656,"tree-cover-loss-percent-per-year":0.0055,"redd-plus-finance":8,"development-finance":25,"results-based-finance-commitments":0},{"country-id":"NA","slug":"namibia","latitude":-22,"longitude":17,"name":"Namibia","tree-cover-loss":130,"tree-cover-loss-percent-per-year":0.0057,"redd-plus-finance":0,"development-finance":1,"results-based-finance-commitments":0},{"country-id":"NP","slug":"nepal","latitude":28,"longitude":84,"name":"Nepal","tree-cover-loss":12786,"tree-cover-loss-percent-per-year":0.0004,"redd-plus-finance":9.818,"development-finance":34,"results-based-finance-commitments":70},{"country-id":"NI","slug":"nicaragua","latitude":13,"longitude":-85,"name":"Nicaragua","tree-cover-loss":444658,"tree-cover-loss-percent-per-year":0.0095,"redd-plus-finance":9.1,"development-finance":13,"results-based-finance-commitments":55},{"country-id":"NG","slug":"nigeria","latitude":10,"longitude":8,"name":"Nigeria","tree-cover-loss":274644,"tree-cover-loss-percent-per-year":0.0046,"redd-plus-finance":8,"development-finance":null,"results-based-finance-commitments":0},{"country-id":"KP","slug":"north-korea","latitude":40,"longitude":127,"name":"North Korea","tree-cover-loss":67960,"tree-cover-loss-percent-per-year":0.0022,"redd-plus-finance":0,"development-finance":null,"results-based-finance-commitments":0},{"country-id":"PK","slug":"pakistan","latitude":30,"longitude":70,"name":"Pakistan","tree-cover-loss":1523,"tree-cover-loss-percent-per-year":0.0003,"redd-plus-finance":4,"development-finance":9,"results-based-finance-commitments":0},{"country-id":"PW","slug":"palau","latitude":7.5,"longitude":134.6,"name":"Palau","tree-cover-loss":206,"tree-cover-loss-percent-per-year":0.0008,"redd-plus-finance":0,"development-finance":null,"results-based-finance-commitments":0},{"country-id":"PS","slug":"palestine","latitude":31.5,"longitude":34.5,"name":"Palestine","tree-cover-loss":4,"tree-cover-loss-percent-per-year":0.001,"redd-plus-finance":0,"development-finance":null,"results-based-finance-commitments":0},{"country-id":"PA","slug":"panama","latitude":9,"longitude":-80,"name":"Panama","tree-cover-loss":94181,"tree-cover-loss-percent-per-year":0.0028,"redd-plus-finance":12,"development-finance":3,"results-based-finance-commitments":0},{"country-id":"PG","slug":"papua-new-guinea","latitude":-6,"longitude":147,"name":"Papua New Guinea","tree-cover-loss":538312,"tree-cover-loss-percent-per-year":0.0021,"redd-plus-finance":14,"development-finance":18,"results-based-finance-commitments":0},{"country-id":"PY","slug":"paraguay","latitude":-23,"longitude":-58,"name":"Paraguay","tree-cover-loss":2353402,"tree-cover-loss-percent-per-year":0.0161,"redd-plus-finance":11,"development-finance":5,"results-based-finance-commitments":0},{"country-id":"PE","slug":"peru","latitude":-10,"longitude":-76,"name":"Peru","tree-cover-loss":1124439,"tree-cover-loss-percent-per-year":0.0024,"redd-plus-finance":43.98,"development-finance":30,"results-based-finance-commitments":274},{"country-id":"PH","slug":"philippines","latitude":13,"longitude":122,"name":"Philippines","tree-cover-loss":422712,"tree-cover-loss-percent-per-year":0.0038,"redd-plus-finance":14,"development-finance":121,"results-based-finance-commitments":0},{"country-id":"CG","slug":"republic-of-congo","latitude":-1,"longitude":15,"name":"Republic of Congo","tree-cover-loss":280492,"tree-cover-loss-percent-per-year":0.0018,"redd-plus-finance":13,"development-finance":8,"results-based-finance-commitments":58.5},{"country-id":"RW","slug":"rwanda","latitude":-2,"longitude":30,"name":"Rwanda","tree-cover-loss":12071,"tree-cover-loss-percent-per-year":0.004,"redd-plus-finance":0,"development-finance":19,"results-based-finance-commitments":0},{"country-id":"KN","slug":"saint-kitts-and-nevis","latitude":17.3,"longitude":-62.7,"name":"Saint Kitts and Nevis","tree-cover-loss":52,"tree-cover-loss-percent-per-year":0.0007,"redd-plus-finance":0,"development-finance":null,"results-based-finance-commitments":0},{"country-id":"LC","slug":"saint-lucia","latitude":14,"longitude":-61,"name":"Saint Lucia","tree-cover-loss":313,"tree-cover-loss-percent-per-year":0.001,"redd-plus-finance":0,"development-finance":null,"results-based-finance-commitments":0},{"country-id":"VC","slug":"saint-vincent-and-the-grenadines","latitude":13.16,"longitude":-61.2,"name":"Saint Vincent and the Grenadines","tree-cover-loss":147,"tree-cover-loss-percent-per-year":0.0008,"redd-plus-finance":0,"development-finance":null,"results-based-finance-commitments":0},{"country-id":"SM","slug":"san-marino","latitude":43.9,"longitude":12.4,"name":"San Marino","tree-cover-loss":1,"tree-cover-loss-percent-per-year":0.0002,"redd-plus-finance":0,"development-finance":null,"results-based-finance-commitments":0},{"country-id":"SN","slug":"senegal","latitude":14,"longitude":-14,"name":"Senegal","tree-cover-loss":1350,"tree-cover-loss-percent-per-year":0.0057,"redd-plus-finance":0,"development-finance":4,"results-based-finance-commitments":0},{"country-id":"RS","slug":"serbia","latitude":44,"longitude":21,"name":"Serbia","tree-cover-loss":18152,"tree-cover-loss-percent-per-year":0.0011,"redd-plus-finance":0,"development-finance":1,"results-based-finance-commitments":0},{"country-id":"SC","slug":"seychelles","latitude":-4.6,"longitude":55.5,"name":"Seychelles","tree-cover-loss":4,"tree-cover-loss-percent-per-year":0.0001,"redd-plus-finance":0,"development-finance":null,"results-based-finance-commitments":0},{"country-id":"SL","slug":"sierra-leone","latitude":8.5,"longitude":-11.5,"name":"Sierra Leone","tree-cover-loss":623620,"tree-cover-loss-percent-per-year":0.0185,"redd-plus-finance":0,"development-finance":null,"results-based-finance-commitments":0},{"country-id":"SG","slug":"singapore","latitude":1.3667,"longitude":103.8,"name":"Singapore","tree-cover-loss":582,"tree-cover-loss-percent-per-year":0.0052,"redd-plus-finance":0,"development-finance":null,"results-based-finance-commitments":0},{"country-id":"SB","slug":"solomon-islands","latitude":-8,"longitude":159,"name":"Solomon Islands","tree-cover-loss":62466,"tree-cover-loss-percent-per-year":0.0038,"redd-plus-finance":1,"development-finance":8,"results-based-finance-commitments":0},{"country-id":"SO","slug":"somalia","latitude":10,"longitude":49,"name":"Somalia","tree-cover-loss":1024,"tree-cover-loss-percent-per-year":0.002,"redd-plus-finance":0,"development-finance":0,"results-based-finance-commitments":0},{"country-id":"ZA","slug":"south-africa","latitude":-29,"longitude":24,"name":"South Africa","tree-cover-loss":412465,"tree-cover-loss-percent-per-year":0.0115,"redd-plus-finance":0,"development-finance":null,"results-based-finance-commitments":0},{"country-id":"KR","slug":"south-korea","latitude":37,"longitude":127.5,"name":"South Korea","tree-cover-loss":82313,"tree-cover-loss-percent-per-year":0.0026,"redd-plus-finance":0,"development-finance":null,"results-based-finance-commitments":0},{"country-id":"SS","slug":"south-sudan","latitude":4.8,"longitude":31.6,"name":"South Sudan","tree-cover-loss":33678,"tree-cover-loss-percent-per-year":0.0005,"redd-plus-finance":0,"development-finance":0,"results-based-finance-commitments":0},{"country-id":"LK","slug":"sri-lanka","latitude":7,"longitude":81,"name":"Sri Lanka","tree-cover-loss":64102,"tree-cover-loss-percent-per-year":0.0027,"redd-plus-finance":4,"development-finance":0,"results-based-finance-commitments":0},{"country-id":"SD","slug":"sudan","latitude":15,"longitude":30,"name":"Sudan","tree-cover-loss":283,"tree-cover-loss-percent-per-year":0.0006,"redd-plus-finance":4,"development-finance":0,"results-based-finance-commitments":0},{"country-id":"SR","slug":"suriname","latitude":4,"longitude":-56,"name":"Suriname","tree-cover-loss":69071,"tree-cover-loss-percent-per-year":0.0008,"redd-plus-finance":4,"development-finance":1,"results-based-finance-commitments":0},{"country-id":"SZ","slug":"swaziland","latitude":-26.5,"longitude":31.5,"name":"Swaziland","tree-cover-loss":24112,"tree-cover-loss-percent-per-year":0.0086,"redd-plus-finance":0,"development-finance":0,"results-based-finance-commitments":0},{"country-id":"SY","slug":"syria","latitude":35,"longitude":38,"name":"Syria","tree-cover-loss":10389,"tree-cover-loss-percent-per-year":0.0163,"redd-plus-finance":0,"development-finance":null,"results-based-finance-commitments":0},{"country-id":"TJ","slug":"tajikistan","latitude":39,"longitude":71,"name":"Tajikistan","tree-cover-loss":59,"tree-cover-loss-percent-per-year":0.0002,"redd-plus-finance":0,"development-finance":0,"results-based-finance-commitments":0},{"country-id":"TZ","slug":"tanzania","latitude":-6,"longitude":35,"name":"Tanzania","tree-cover-loss":922424,"tree-cover-loss-percent-per-year":0.0058,"redd-plus-finance":65,"development-finance":23,"results-based-finance-commitments":0},{"country-id":"TH","slug":"thailand","latitude":15,"longitude":100,"name":"Thailand","tree-cover-loss":687214,"tree-cover-loss-percent-per-year":0.0057,"redd-plus-finance":6,"development-finance":5,"results-based-finance-commitments":0},{"country-id":"TL","slug":"timor-leste","latitude":-8.9,"longitude":125.9,"name":"Timor-Leste","tree-cover-loss":7207,"tree-cover-loss-percent-per-year":0.0017,"redd-plus-finance":0,"development-finance":5,"results-based-finance-commitments":0},{"country-id":"TG","slug":"togo","latitude":8,"longitude":1.1667,"name":"Togo","tree-cover-loss":9936,"tree-cover-loss-percent-per-year":0.003,"redd-plus-finance":5.376,"development-finance":7,"results-based-finance-commitments":0},{"country-id":"TT","slug":"trinidad-and-tobago","latitude":11,"longitude":-61,"name":"Trinidad and Tobago","tree-cover-loss":7492,"tree-cover-loss-percent-per-year":0.0032,"redd-plus-finance":0,"development-finance":null,"results-based-finance-commitments":0},{"country-id":"TN","slug":"tunisia","latitude":34,"longitude":9,"name":"Tunisia","tree-cover-loss":9582,"tree-cover-loss-percent-per-year":0.0071,"redd-plus-finance":0,"development-finance":2,"results-based-finance-commitments":0},{"country-id":"TM","slug":"turkmenistan","latitude":40,"longitude":60,"name":"Turkmenistan","tree-cover-loss":36,"tree-cover-loss-percent-per-year":0.0006,"redd-plus-finance":0,"development-finance":null,"results-based-finance-commitments":0},{"country-id":"UG","slug":"uganda","latitude":1,"longitude":32,"name":"Uganda","tree-cover-loss":285131,"tree-cover-loss-percent-per-year":0.0061,"redd-plus-finance":6,"development-finance":22,"results-based-finance-commitments":0},{"country-id":"UY","slug":"uruguay","latitude":-33,"longitude":-56,"name":"Uruguay","tree-cover-loss":139669,"tree-cover-loss-percent-per-year":0.0137,"redd-plus-finance":4,"development-finance":40,"results-based-finance-commitments":0},{"country-id":"UZ","slug":"uzbekistan","latitude":41,"longitude":64,"name":"Uzbekistan","tree-cover-loss":229,"tree-cover-loss-percent-per-year":0.0004,"redd-plus-finance":0,"development-finance":3,"results-based-finance-commitments":0},{"country-id":"VU","slug":"vanuatu","latitude":-17.7,"longitude":168.3,"name":"Vanuatu","tree-cover-loss":6335,"tree-cover-loss-percent-per-year":0.0009,"redd-plus-finance":4,"development-finance":1,"results-based-finance-commitments":0},{"country-id":"VE","slug":"venezuela","latitude":8,"longitude":-66,"name":"Venezuela","tree-cover-loss":508621,"tree-cover-loss-percent-per-year":0.0015,"redd-plus-finance":0,"development-finance":8,"results-based-finance-commitments":0},{"country-id":"VN","slug":"vietnam","latitude":16,"longitude":106,"name":"Vietnam","tree-cover-loss":1054323,"tree-cover-loss-percent-per-year":0.0106,"redd-plus-finance":25.185,"development-finance":168,"results-based-finance-commitments":51.5},{"country-id":"ZM","slug":"zambia","latitude":-15,"longitude":30,"name":"Zambia","tree-cover-loss":651755,"tree-cover-loss-percent-per-year":0.0045,"redd-plus-finance":18,"development-finance":16,"results-based-finance-commitments":30},{"country-id":"ZW","slug":"zimbabwe","latitude":-20,"longitude":30,"name":"Zimbabwe","tree-cover-loss":61015,"tree-cover-loss-percent-per-year":0.0072,"redd-plus-finance":0,"development-finance":0,"results-based-finance-commitments":0}]